Metadata-Version: 1.1
Name: flake8-todo
Version: 0.7
Summary: TODO notes checker, plugin for flake8
Home-page: https://github.com/schlamar/flake8-todo
Author: Marc Schlaich
Author-email: marc.schlaich@gmail.com
License: MIT
Keywords: flake8 todo
Platform: UNKNOWN
Classifier: Framework :: Flake8
Classifier: Development Status :: 4 - Beta
Classifier: Environment :: Console
Classifier: Intended Audience :: Developers
Classifier: License :: OSI Approved :: MIT License
Classifier: Operating System :: OS Independent
Classifier: Programming Language :: Python
Classifier: Programming Language :: Python :: 2
Classifier: Programming Language :: Python :: 3
Classifier: Topic :: Software Development :: Libraries :: Python Modules
Classifier: Topic :: Software Development :: Quality Assurance
